odoo/addons/purchase_packaging/README.rst
odoo/addons/purchase_packaging/__init__.py
odoo/addons/purchase_packaging/__manifest__.py
odoo/addons/purchase_packaging/hooks.py
odoo/addons/purchase_packaging/i18n/ca.po
odoo/addons/purchase_packaging/i18n/cs_CZ.po
odoo/addons/purchase_packaging/i18n/de.po
odoo/addons/purchase_packaging/i18n/es.po
odoo/addons/purchase_packaging/i18n/es_ES.po
odoo/addons/purchase_packaging/i18n/es_MX.po
odoo/addons/purchase_packaging/i18n/fi.po
odoo/addons/purchase_packaging/i18n/fr.po
odoo/addons/purchase_packaging/i18n/fr_CH.po
odoo/addons/purchase_packaging/i18n/hr.po
odoo/addons/purchase_packaging/i18n/hr_HR.po
odoo/addons/purchase_packaging/i18n/it.po
odoo/addons/purchase_packaging/i18n/nl.po
odoo/addons/purchase_packaging/i18n/nl_NL.po
odoo/addons/purchase_packaging/i18n/pt_BR.po
odoo/addons/purchase_packaging/i18n/pt_PT.po
odoo/addons/purchase_packaging/i18n/purchase_packaging.pot
odoo/addons/purchase_packaging/i18n/ro.po
odoo/addons/purchase_packaging/i18n/sk.po
odoo/addons/purchase_packaging/i18n/sl.po
odoo/addons/purchase_packaging/i18n/tr.po
odoo/addons/purchase_packaging/i18n/tr_TR.po
odoo/addons/purchase_packaging/i18n/vi_VN.po
odoo/addons/purchase_packaging/i18n/zh_CN.po
odoo/addons/purchase_packaging/models/__init__.py
odoo/addons/purchase_packaging/models/product_supplier_info.py
odoo/addons/purchase_packaging/models/purchase_order_line.py
odoo/addons/purchase_packaging/models/stock_rule.py
odoo/addons/purchase_packaging/models/stock_warehouse_orderpoint.py
odoo/addons/purchase_packaging/models/uom.py
odoo/addons/purchase_packaging/readme/CONFIGURE.rst
odoo/addons/purchase_packaging/readme/CONTRIBUTORS.rst
odoo/addons/purchase_packaging/readme/DESCRIPTION.rst
odoo/addons/purchase_packaging/static/description/icon.png
odoo/addons/purchase_packaging/static/description/index.html
odoo/addons/purchase_packaging/tests/__init__.py
odoo/addons/purchase_packaging/tests/test_procurement_order.py
odoo13_addon_purchase_packaging-13.0.1.0.1.dev13.dist-info/METADATA
odoo13_addon_purchase_packaging-13.0.1.0.1.dev13.dist-info/WHEEL
odoo13_addon_purchase_packaging-13.0.1.0.1.dev13.dist-info/top_level.txt
odoo13_addon_purchase_packaging-13.0.1.0.1.dev13.dist-info/RECORD
