Metadata-Version: 2.1
Name: odoo13-addon-purchase_packaging
Version: 13.0.1.0.1.dev13
Summary: In purchase, use package
Home-page: https://github.com/OCA/purchase-workflow
Author: ACSONE SA/NV, Odoo Community Association (OCA)
Author-email: support@odoo-community.org
License: AGPL-3
Classifier: Programming Language :: Python
Classifier: Framework :: Odoo
Classifier: Framework :: Odoo :: 13.0
Classifier: License :: OSI Approved :: GNU Affero General Public License v3
Requires-Python: >=3.5
Requires-Dist: odoo13-addon-packaging-uom
Requires-Dist: odoo <13.1dev,>=13.0a
